automedia/docker.py
automedia/ffmpeg.py
automedia/ffmpeg_transcoder.py
automedia/ffmpeg_validator.py
automedia/forward_progress.py
automedia/jobqueue.py
automedia/main.py
automedia/operation.py
automedia/par2.py
automedia/path_scan.py
automedia-0.9.dist-info/LICENSE
automedia-0.9.dist-info/METADATA
automedia-0.9.dist-info/WHEEL
automedia-0.9.dist-info/entry_points.txt
automedia-0.9.dist-info/top_level.txt
automedia-0.9.dist-info/RECORD
