Metadata-Version: 2.1
Name: automedia
Version: 0.9
Summary: Automedia is a tool to manage large media libraries, whether it be audio or video.
Author-email: Matt Mastracci <matthew@mastracci.com>, Estefania Barreto-Ojeda <estefania@ojeda-e.com>
License: GNU General Public License v3 (GPLv3)
License-File: LICENSE
